streamlit_custom_chat/__init__.py
streamlit_custom_chat/frontend/build/asset-manifest.json
streamlit_custom_chat/frontend/build/bootstrap.min.css
streamlit_custom_chat/frontend/build/index.html
streamlit_custom_chat/frontend/build/person_icon.png
streamlit_custom_chat/frontend/build/robot_icon.png
streamlit_custom_chat/frontend/build/static/css/main.241951ba.css
streamlit_custom_chat/frontend/build/static/css/main.241951ba.css.map
streamlit_custom_chat/frontend/build/static/js/main.c4ab80ec.js
streamlit_custom_chat/frontend/build/static/js/main.c4ab80ec.js.LICENSE.txt
streamlit_custom_chat/frontend/build/static/js/main.c4ab80ec.js.map
streamlit_custom_chat-0.1.2.dist-info/LICENSE
streamlit_custom_chat-0.1.2.dist-info/METADATA
streamlit_custom_chat-0.1.2.dist-info/WHEEL
streamlit_custom_chat-0.1.2.dist-info/top_level.txt
streamlit_custom_chat-0.1.2.dist-info/RECORD
